appomni/data/spellbook_utils/__init__.py
appomni/data/spellbook_utils/globals.py
appomni/data/spellbook_utils/schemas.py
appomni_spellbook_utils-0.1.22.dist-info/LICENSE.md
appomni_spellbook_utils-0.1.22.dist-info/METADATA
appomni_spellbook_utils-0.1.22.dist-info/WHEEL
appomni_spellbook_utils-0.1.22.dist-info/RECORD
