Metadata-Version: 2.3
Name: appomni-spellbook-utils
Version: 0.1.22
Summary: 
Author: AppOmni Engineering
Author-email: aopython@appomni.com
Requires-Python: >=3.10,<4.0
Classifier: License :: OSI Approved :: MIT License
Classifier: Programming Language :: Python :: 3
Classifier: Programming Language :: Python :: 3.10
Classifier: Programming Language :: Python :: 3.11
Classifier: Programming Language :: Python :: 3.12
Classifier: Programming Language :: Python :: 3.13
Classifier: Topic :: Software Development :: Libraries
Requires-Dist: attrs (>=22.1.0)
Requires-Dist: cattrs (>=22.2.0)
Requires-Dist: glom (>=22.1.0)
Requires-Dist: pyyaml (>=6.0)
